addthreenumbers/__init__.py
addthreenumbers-0.2.3.dist-info/METADATA
addthreenumbers-0.2.3.dist-info/WHEEL
addthreenumbers-0.2.3.dist-info/top_level.txt
addthreenumbers-0.2.3.dist-info/RECORD
