Metadata-Version: 2.1
Name: addthreenumbers
Version: 0.2.3
Summary: A simple library to add three numbers
Author: Your Name
Author-email: your@email.com
Classifier: License :: OSI Approved :: MIT License
Classifier: Programming Language :: Python
Classifier: Programming Language :: Python :: 3
Classifier: Programming Language :: Python :: 3.6
Classifier: Programming Language :: Python :: 3.7
Classifier: Programming Language :: Python :: 3.8
Classifier: Programming Language :: Python :: 3.9
